pyconverter/__init__.py
pyconverter/avcodecs.py
pyconverter/ffmpeg.py
pyconverter/formats.py
pyconverter/version.py
pyconverter-1.0.0.dist-info/AUTHORS.txt
pyconverter-1.0.0.dist-info/METADATA
pyconverter-1.0.0.dist-info/WHEEL
pyconverter-1.0.0.dist-info/top_level.txt
pyconverter-1.0.0.dist-info/zip-safe
pyconverter-1.0.0.dist-info/RECORD
