Metadata-Version: 2.1
Name: pyconverter
Version: 1.0.0
Summary: Python 3 library for short text
Home-page: https://github.com/fenixinvitado2021/shorturl
Author: RayServer
Author-email: susej.mabel2009@gmail.com
License: The Unlicense (Unlicense)
Keywords: convert
Classifier: Development Status :: 5 - Production/Stable
Classifier: Environment :: Console
Classifier: Intended Audience :: Developers
Classifier: License :: OSI Approved :: The Unlicense (Unlicense)
Classifier: Natural Language :: English
Classifier: Operating System :: OS Independent
Classifier: Programming Language :: Python :: 3.6
Classifier: Programming Language :: Python :: 3.7
Classifier: Programming Language :: Python :: 3.8
Classifier: Programming Language :: Python :: 3.9
Classifier: Programming Language :: Python
Classifier: Topic :: Internet
Classifier: Topic :: Software Development :: Libraries :: Python Modules
Classifier: Topic :: Utilities
License-File: AUTHORS.txt
Requires-Dist: bs4 ==0.0.1
